ai_minecraft_image/__init__.py
ai_minecraft_image-1768297.318.754.dist-info/licenses/LICENSE
ai_minecraft_image-1768297.318.754.dist-info/METADATA
ai_minecraft_image-1768297.318.754.dist-info/WHEEL
ai_minecraft_image-1768297.318.754.dist-info/top_level.txt
ai_minecraft_image-1768297.318.754.dist-info/RECORD
