Metadata-Version: 2.4
Name: ai-minecraft-image
Version: 1768297.318.754
Summary: High-quality integration for https://supermaker.ai/image/blog/how-to-turn-your-image-into-minecraft-skin/
Home-page: https://supermaker.ai/image/blog/how-to-turn-your-image-into-minecraft-skin/
Author: SuperMaker
Classifier: Programming Language :: Python :: 3
Classifier: License :: OSI Approved :: MIT License
Requires-Python: >=3.6
License-File: LICENSE
Dynamic: author
Dynamic: classifier
Dynamic: description
Dynamic: description-content-type
Dynamic: home-page
Dynamic: license-file
Dynamic: requires-python
Dynamic: summary
